login/__init__.py
login/__main__.py
login/aws_oidc_login.py
login/config.py
login/credentials.py
login/jwt.py
login/oidc_authorizer.py
aws_oidc_login-0.2.0.dist-info/LICENSE
aws_oidc_login-0.2.0.dist-info/METADATA
aws_oidc_login-0.2.0.dist-info/WHEEL
aws_oidc_login-0.2.0.dist-info/entry_points.txt
aws_oidc_login-0.2.0.dist-info/top_level.txt
aws_oidc_login-0.2.0.dist-info/RECORD
