Metadata-Version: 2.1
Name: aws-oidc-login
Version: 0.2.0
Summary: CLI login to AWS using OpenID Connect
Home-page: http://github.com/NitorCreations/aws-oidc-login
Author: Mika Majakorpi
Author-email: mika.majakorpi@nitor.com
License: Apache 2.0
Download-URL: https://github.com/NitorCreations/aws-oidc-login
Platform: UNKNOWN
Requires-Dist: boto3 (==1.9.208)
Requires-Dist: requests (==2.22.0)
Requires-Dist: argparse (==1.4.0)
